gdbplotlib/__init__.py
gdbplotlib/data_extractor.py
gdbplotlib/default.py
gdbplotlib/plot.py
gdbplotlib/save.py
gdbplotlib/std_types.py
gdbplotlib/type_handler.py
gdbplotlib/type_set.py
gdbplotlib/util.py
gdbplotlib-0.3.0.dist-info/LICENSE
gdbplotlib-0.3.0.dist-info/METADATA
gdbplotlib-0.3.0.dist-info/WHEEL
gdbplotlib-0.3.0.dist-info/top_level.txt
gdbplotlib-0.3.0.dist-info/RECORD
