Metadata-Version: 2.1
Name: gdbplotlib
Version: 0.3.0
Summary: Plotting and exporting of variables from GDB
Home-page: https://github.com/X-Neon/gdbplotlib
Author: George Cholerton
Author-email: gcholerton@gmail.com
Keywords: gdb,debug
Classifier: Development Status :: 3 - Alpha
Classifier: Intended Audience :: Developers
Classifier: Intended Audience :: Science/Research
Classifier: License :: OSI Approved :: MIT License
Classifier: Programming Language :: Python :: 3
Classifier: Topic :: Scientific/Engineering :: Visualization
Classifier: Topic :: Software Development :: Debuggers
Requires-Python: >=3
License-File: LICENSE
Requires-Dist: numpy
Requires-Dist: matplotlib
